osc_data-0.2.6.dist-info/METADATA
osc_data-0.2.6.dist-info/WHEEL
osc_data/__init__.py
osc_data/_core.cpython-39-x86_64-linux-gnu.so
osc_data/assets/audio/example.wav
osc_data/assets/text/tn/tagger.fst
osc_data/assets/text/tn/verbalizer.fst
osc_data/assets/text/tn/verbalizer_remove_erhua.fst
osc_data/audio.py
osc_data/text.py
osc_data/text_stream.py
osc_data/video.py
osc_data-0.2.6.dist-info/RECORD
