Metadata-Version: 2.4
Name: osc-data
Version: 0.2.6
Requires-Dist: kaldifst>=1.7.14
Requires-Dist: pydantic>=2.11.7
Requires-Dist: docarray
Requires-Dist: requests>=2.32.5
Requires-Dist: librosa>=0.11.0
Requires-Dist: av>=10.0.0
Summary: data represent, processing
Author-email: wangmengdi <790990241@qq.com>
Requires-Python: >=3.9
